quartic_bspline_extension/__init__.py
quartic_bspline_extension/bindings.cpp
quartic_bspline_extension/functions.py
quartic_bspline_extension/quartic_backward_cpu_kernel.cpp
quartic_bspline_extension/quartic_bspline_extension.cpython-311-x86_64-linux-gnu.so
quartic_bspline_extension/quartic_forward_cpu_kernel.cpp
quartic_bspline_extension/include/constants.h
quartic_bspline_extension/include/debug_utils.cuh
quartic_bspline_extension/include/device_utils.h
quartic_bspline_extension/include/index_utils.h
quartic_bspline_extension-0.3.0.dist-info/METADATA
quartic_bspline_extension-0.3.0.dist-info/WHEEL
quartic_bspline_extension-0.3.0.dist-info/top_level.txt
quartic_bspline_extension-0.3.0.dist-info/RECORD
