Metadata-Version: 2.4
Name: quartic_bspline_extension
Version: 0.3.0
Summary: Quartic B-Spline extension: CPU and CUDA extension for quartic bspline based potential functions.
Author-email: "Florian Thaler, Thomas Pock" <florian.thaler@tugraz.at>
Maintainer-email: Florian Thaler <florian.thaler@tugraz.at>
License-Expression: MIT
Project-URL: Homepage, https://github.com/VLOGroup/quartic_bspline_extension
Keywords: Quartic B-Spline
Classifier: Programming Language :: Python :: 3
Classifier: Programming Language :: C++
Requires-Python: >=3.11
Requires-Dist: torch>=2.6.0
Dynamic: requires-python
